surfboard_exporter/__init__.py
surfboard_exporter/collector.py
surfboard_exporter/http.py
surfboard_exporter-1.0.0.data/scripts/surfboard_exporter
surfboard_exporter-1.0.0.dist-info/DESCRIPTION.rst
surfboard_exporter-1.0.0.dist-info/METADATA
surfboard_exporter-1.0.0.dist-info/RECORD
surfboard_exporter-1.0.0.dist-info/WHEEL
surfboard_exporter-1.0.0.dist-info/metadata.json
surfboard_exporter-1.0.0.dist-info/top_level.txt
