Metadata-Version: 2.0
Name: surfboard-exporter
Version: 1.0.0
Summary: Arris Surfboard exporter for the Prometheus monitoring system.
Home-page: https://github.com/ipstatic/surfboard_exporter
Author: Jarod Watkins
Author-email: jwatkins@jarodw.com
License: MIT
Keywords: prometheus exporter monitoring arris surfboard modem
Platform: UNKNOWN
Classifier: Development Status :: 3 - Alpha
Classifier: Intended Audience :: Information Technology
Classifier: Intended Audience :: System Administrators
Classifier: Topic :: System :: Monitoring
Classifier: License :: OSI Approved :: MIT License
Requires-Dist: lxml (>=3.2.1)
Requires-Dist: prometheus-client (>=0.0.14)
Requires-Dist: requests (>=2.6.0)
